<PAMDataset>
  <PAMRasterBand band="1">
    <Histograms>
      <HistItem>
        <HistMin>1</HistMin>
        <HistMax>244</HistMax>
        <BucketCount>256</BucketCount>
        <IncludeOutOfRange>1</IncludeOutOfRange>
        <Approximate>0</Approximate>
        <HistCounts>315|441|755|974|1274|1564|1763|1828|1631|1567|1503|1312|1283|1123|1063|1058|862|960|919|0|843|888|925|873|941|808|880|859|832|847|881|823|818|862|821|800|813|779|894|0|821|839|822|820|880|821|809|825|887|839|800|767|842|828|815|890|868|838|807|0|875|830|841|819|853|901|815|859|886|780|813|860|790|801|877|792|782|833|0|808|810|826|823|793|779|821|840|826|722|802|824|809|763|798|815|803|782|764|0|754|763|731|786|748|738|753|754|746|786|726|740|724|702|704|718|663|698|695|0|654|639|653|707|707|667|650|707|647|654|620|673|701|614|623|639|602|648|0|574|651|583|612|647|552|612|610|582|516|595|611|599|615|562|551|621|564|587|0|533|545|554|493|540|579|506|507|558|545|505|490|496|466|529|467|548|521|500|0|451|428|426|463|436|426|471|472|451|416|456|430|370|364|385|365|380|372|0|372|349|382|330|322|331|337|318|334|289|335|282|293|264|296|279|243|245|230|0|217|232|232|199|200|190|196|203|152|164|148|186|136|139|142|124|119|120|116|0|102|94|90|94|81|43|55|44|23|15|15|2|9|9|1|0|0|1|1</HistCounts>
      </HistItem>
    </Histograms>
    <Metadata>
      <MDI key="RepresentationType">ATHEMATIC</MDI>
      <MDI key="STATISTICS_EXCLUDEDVALUES"></MDI>
      <MDI key="STATISTICS_MAXIMUM">244</MDI>
      <MDI key="STATISTICS_MEAN">88.42370861997</MDI>
      <MDI key="STATISTICS_MINIMUM">1</MDI>
      <MDI key="STATISTICS_SKIPFACTORX">1</MDI>
      <MDI key="STATISTICS_SKIPFACTORY">1</MDI>
      <MDI key="STATISTICS_STDDEV">59.308314312494</MDI>
    </Metadata>
  </PAMRasterBand>
</PAMDataset>
